{
  "flow_id": "flow_topic_6ZVj1_SE4Mo_Privacy_topic_xYMWTXIkANM_Pegasus_Spyware",
  "source_node": {
    "node_id": "topic_6ZVj1_SE4Mo_Privacy",
    "concept_name": "Privacy",
    "video_id": "6ZVj1_SE4Mo",
    "video_title": "Global Spyware Scandal: Exposing Pegasus Part One (full documentary) | FRONTLINE",
    "timestamp": 0,
    "maturity_level": "mentioned",
    "context": "The potential use of Pegasus against figures like Jamal Khashoggi, who was killed in 2018, highlights the severe real-world implications of this technology for privacy, human rights, and democratic processes.",
    "explanation_depth": 0.85,
    "key_points": [],
    "related_entities": [
      "Jamal Khashoggi",
      "Jamal",
      "Pegasus",
      "Jamal Khashoggi",
      "Pegasus"
    ],
    "sentiment": 0.0,
    "confidence": 0.85,
    "information_density": 0.3,
    "video_sequence_position": 0
  },
  "target_node": {
    "node_id": "topic_xYMWTXIkANM_Pegasus_Spyware",
    "concept_name": "Pegasus Spyware",
    "video_id": "xYMWTXIkANM",
    "video_title": "Global Spyware Scandal: Exposing Pegasus Part Two (full documentary) | FRONTLINE",
    "timestamp": 0,
    "maturity_level": "mentioned",
    "context": "Topic 'Pegasus Spyware' discussed in video",
    "explanation_depth": 0.85,
    "key_points": [],
    "related_entities": [
      "Pegasus",
      "Pegasus",
      "Pegasus"
    ],
    "sentiment": 0.0,
    "confidence": 0.85,
    "information_density": 0.3,
    "video_sequence_position": 1
  },
  "flow_type": "synthesis",
  "information_transferred": "Connecting Privacy to Pegasus Spyware",
  "transformation_type": "integration",
  "flow_quality": 0.95,
  "coherence_score": 0.1,
  "temporal_gap": 3600,
  "bridge_entities": [
    "Pegasus"
  ],
  "supporting_evidence": [
    "The potential use of Pegasus against figures like Jamal Khashoggi, who was killed in 2018, highlights the severe real-world implications of this technology for privacy, human rights, and democratic processes.",
    "Topic 'Pegasus Spyware' discussed in video"
  ]
}